ctfcicd/__init__.py
ctfcicd/__main__.py
ctfcicd/cicd.py
ctfcicd/utils/__init__.py
ctfcicd/utils/api.py
ctfcicd/utils/challenge.py
ctfcicd/utils/config.py
ctfcicd/utils/deploy.py
ctfcicd/utils/images.py
ctfcicd-1.2.0.dist-info/LICENSE
ctfcicd-1.2.0.dist-info/METADATA
ctfcicd-1.2.0.dist-info/WHEEL
ctfcicd-1.2.0.dist-info/entry_points.txt
ctfcicd-1.2.0.dist-info/top_level.txt
ctfcicd-1.2.0.dist-info/RECORD
