Metadata-Version: 2.1
Name: ctfcicd
Version: 1.2.0
Summary: Tool for CI/CD pipelines to deploy CTFs
Author: André Cirne
Project-URL: Homepage, https://github.com/MrSuicideParrot/ctf-cicd
Project-URL: Repository, https://github.com/MrSuicideParrot/ctf-cicd
Classifier: Programming Language :: Python
Requires-Python: >=3.9
License-File: LICENSE
Requires-Dist: docker ~=5.0.2
Requires-Dist: requests ~=2.22.0
Requires-Dist: PyYAML
Requires-Dist: paramiko
